{"MatMul": ["Placeholder"], "MatMul_1": ["Placeholder_1"], "X0/max": [], "X1/mul": ["X1/sub", "X1/RandomUniform"], "Placeholder": [], "X0/RandomUniform": ["X0/shape"], "X0/min": [], "Add": ["MatMul"], "X0/mul": ["X0/sub", "X0/RandomUniform"], "Add_1": ["MatMul_1"], "X0/sub": ["X0/min", "X0/max"], "Placeholder_1": [], "X1/shape": [], "X1/min": [], "X1/max": [], "X0": ["X0/min", "X0/mul"], "X1": ["X1/mul", "X1/min"], "X1/sub": ["X1/max", "X1/min"], "X0/shape": [], "X1/RandomUniform": ["X1/shape"]}